SimuladorBohr/__init__.py
SimuladorBohr/constants.py
SimuladorBohr/energy.py
SimuladorBohr/plotting.py
SimuladorBohr/radius.py
SimuladorBohr/transitions.py
simuladorbohr-0.1.0.dist-info/licenses/LICENSE
simuladorbohr-0.1.0.dist-info/METADATA
simuladorbohr-0.1.0.dist-info/WHEEL
simuladorbohr-0.1.0.dist-info/top_level.txt
simuladorbohr-0.1.0.dist-info/RECORD
