Metadata-Version: 2.4
Name: SimuladorBohr
Version: 0.1.0
Summary: Librería en Python para cálculos y visualización del modelo atómico de Bohr para el átomo de hidrogéno e hidrogenoides.
Author-email: Daniel Felipe Ramirez Cabrera <danielpiperc05@gmail.com>, Santiago Criollo Bermudez <santicriollo@hotmail.com>, Nicolas Alexei Duran Amariles <amidamarulas@gmail.com>
License: MIT
Project-URL: Homepage, https://github.com/amidamarulas/SimuladorBohr.git
Project-URL: Repository, https://github.com/amidamarulas/SimuladorBohr.git
Project-URL: Issues, https://github.com/amidamarulas/SimuladorBohr.git
Keywords: physics,bohr,quantum,atomic-model,education
Classifier: Development Status :: 3 - Alpha
Classifier: Programming Language :: Python :: 3
Classifier: Intended Audience :: Education
Classifier: Topic :: Scientific/Engineering :: Physics
Classifier: License :: OSI Approved :: MIT License
Requires-Python: >=3.8
License-File: LICENSE
Requires-Dist: numpy>=1.20
Requires-Dist: matplotlib>=3.5
Dynamic: license-file
